inicheck/__init__.py
inicheck/changes.py
inicheck/checkers.py
inicheck/cli.py
inicheck/config.py
inicheck/entries.py
inicheck/iniparse.py
inicheck/output.py
inicheck/tools.py
inicheck/utilities.py
inicheck-0.9.1.dist-info/AUTHORS.rst
inicheck-0.9.1.dist-info/LICENSE
inicheck-0.9.1.dist-info/METADATA
inicheck-0.9.1.dist-info/WHEEL
inicheck-0.9.1.dist-info/entry_points.txt
inicheck-0.9.1.dist-info/top_level.txt
inicheck-0.9.1.dist-info/RECORD
