Metadata-Version: 2.1
Name: inicheck
Version: 0.9.1
Summary: inicheck is an high level configuration file checker enabling developers tight control over their users configuration files
Home-page: https://github.com/USDA-ARS-NWRC/inicheck
Author: Micah Johnson
Author-email: micah.johnson150@gmail.com
License: GNU General Public License v3
Project-URL: Documentation, https://inicheck.readthedocs.io
Keywords: inicheck
Platform: UNKNOWN
Classifier: Development Status :: 4 - Beta
Classifier: Intended Audience :: Developers
Classifier: License :: OSI Approved :: GNU General Public License v3 (GPLv3)
Classifier: Natural Language :: English
Classifier: Programming Language :: Python :: 3.5
Classifier: Programming Language :: Python :: 3.6
Classifier: Programming Language :: Python :: 3.7
Classifier: Programming Language :: Python :: 3.8
Requires-Dist: dateparser (==0.7.2)
Requires-Dist: requests (>=2.0.0)
Requires-Dist: setuptools-scm (<4.2)
